{
	"$schema": "http://schema.management.azure.com/schemas/2015-01-01/deploymentTemplate.json#",
	"contentVersion": "1.0.0.0",
	"parameters": {
		"factoryName": {
			"type": "string",
			"metadata": "Data Factory name",
			"defaultValue": "bdlsapdatafact"
		}
	},
	"variables": {
		"factoryId": "[concat('Microsoft.DataFactory/factories/', parameters('factoryName'))]"
	},
	"resources": [
		{
			"name": "[concat(parameters('factoryName'), '/NPLProductsTable')]",
			"type": "Microsoft.DataFactory/factories/datasets",
			"apiVersion": "2018-06-01",
			"properties": {
				"linkedServiceName": {
					"referenceName": "NPLTable",
					"type": "LinkedServiceReference"
				},
				"folder": {
					"name": "NPL"
				},
				"annotations": [],
				"type": "SapTableResource",
				"schema": [],
				"typeProperties": {
					"tableName": "SEPMRACSHPRODUCT"
				}
			},
			"dependsOn": [
				"[concat(variables('factoryId'), '/linkedServices/NPLTable')]"
			]
		},
		{
			"name": "[concat(parameters('factoryName'), '/NPLTable')]",
			"type": "Microsoft.DataFactory/factories/linkedServices",
			"apiVersion": "2018-06-01",
			"properties": {
				"annotations": [],
				"type": "SapTable",
				"typeProperties": {
					"clientId": "001",
					"language": "EN",
					"sncMode": false,
					"userName": "ADFUSER",
					"password": {
						"type": "SecureString",
						"value": "**********"
					},
					"server": "137.117.134.161",
					"systemNumber": "00"
				},
				"connectVia": {
					"referenceName": "SAPADFRti",
					"type": "IntegrationRuntimeReference"
				}
			},
			"dependsOn": []
		},
		{
			"name": "[concat(parameters('factoryName'), '/AzDataLakeGen2_NPLProducts_csv_Table')]",
			"type": "Microsoft.DataFactory/factories/datasets",
			"apiVersion": "2018-06-01",
			"properties": {
				"linkedServiceName": {
					"referenceName": "AzDataLakeGen2",
					"type": "LinkedServiceReference"
				},
				"folder": {
					"name": "NPL"
				},
				"annotations": [],
				"type": "DelimitedText",
				"typeProperties": {
					"location": {
						"type": "AzureBlobFSLocation",
						"fileName": {
							"value": "@concat('tableproducts_', formatDateTime(utcnow(),'yyyy-MM-dd-hhmmss'),'.csv')",
							"type": "Expression"
						},
						"folderPath": "NPL/TableConnector",
						"fileSystem": "sap"
					},
					"columnDelimiter": ",",
					"escapeChar": "\\",
					"firstRowAsHeader": true,
					"quoteChar": "\""
				},
				"schema": []
			},
			"dependsOn": []
		},
		{
			"name": "[concat(parameters('factoryName'), '/NPLProductsTable_To_DataLake2')]",
			"type": "Microsoft.DataFactory/factories/pipelines",
			"apiVersion": "2018-06-01",
			"properties": {
				"activities": [
					{
						"name": "NPLProductsTable",
						"type": "Copy",
						"dependsOn": [],
						"policy": {
							"timeout": "7.00:00:00",
							"retry": 0,
							"retryIntervalInSeconds": 30,
							"secureOutput": false,
							"secureInput": false
						},
						"userProperties": [],
						"typeProperties": {
							"source": {
								"type": "SapTableSource",
								"partitionOption": "None"
							},
							"sink": {
								"type": "DelimitedTextSink",
								"storeSettings": {
									"type": "AzureBlobFSWriteSettings"
								},
								"formatSettings": {
									"type": "DelimitedTextWriteSettings",
									"quoteAllText": true,
									"fileExtension": ".txt"
								}
							},
							"enableStaging": false,
							"translator": {
								"type": "TabularTranslator",
								"typeConversion": true,
								"typeConversionSettings": {
									"allowDataTruncation": true,
									"treatBooleanAsNumber": false
								}
							}
						},
						"inputs": [
							{
								"referenceName": "NPLProductsTable",
								"type": "DatasetReference"
							}
						],
						"outputs": [
							{
								"referenceName": "AzDataLakeGen2_NPLProducts_csv_Table",
								"type": "DatasetReference"
							}
						]
					}
				],
				"folder": {
					"name": "NPLProducts"
				},
				"annotations": []
			},
			"dependsOn": [
				"[concat(variables('factoryId'), '/datasets/NPLProductsTable')]",
				"[concat(variables('factoryId'), '/datasets/AzDataLakeGen2_NPLProducts_csv_Table')]"
			]
		}
	]
}